{
  "root_group": {
    "name": "",
    "path": "",
    "id": "d41d8cd98f00b204e9800998ecf8427e",
    "groups": [],
    "checks": [
        {
          "fails": 0,
          "name": "health status é 200 ou 503",
          "path": "::health status é 200 ou 503",
          "id": "0020af24f0c02b4ad812a4aa91af4b40",
          "passes": 10
        },
        {
          "name": "health tem propriedade status",
          "path": "::health tem propriedade status",
          "id": "62f2ab052c1248f6431a78b82ba754d0",
          "passes": 10,
          "fails": 0
        },
        {
          "name": "item status é 200",
          "path": "::item status é 200",
          "id": "6f6bcd83bcce8a55de5823e5415e0616",
          "passes": 10,
          "fails": 0
        },
        {
          "fails": 0,
          "name": "item retorna success",
          "path": "::item retorna success",
          "id": "7ebb286181a636a9955ce5cf200845ce",
          "passes": 10
        },
        {
          "name": "item retorna dados",
          "path": "::item retorna dados",
          "id": "2e214a54032175761bc871095ed58bed",
          "passes": 10,
          "fails": 0
        },
        {
          "fails": 0,
          "name": "resposta em < 500ms",
          "path": "::resposta em < 500ms",
          "id": "4bf8d098c95650ffc6c1295dfb26a0e6",
          "passes": 10
        },
        {
          "name": "item inexistente retorna 404",
          "path": "::item inexistente retorna 404",
          "id": "95b7f8885b6629703d033b6f49da1f83",
          "passes": 10,
          "fails": 0
        },
        {
          "name": "erro tem mensagem",
          "path": "::erro tem mensagem",
          "id": "ecffd0135fc0b2a3b069871d957b8193",
          "passes": 10,
          "fails": 0
        }
      ]
  },
  "options": {
    "summaryTimeUnit": "",
    "noColor": false,
    "summaryTrendStats": [
      "avg",
      "min",
      "med",
      "max",
      "p(90)",
      "p(95)"
    ]
  },
  "state": {
    "isStdOutTTY": true,
    "isStdErrTTY": true,
    "testRunDurationMs": 30170.488158
  },
  "metrics": {
    "http_req_tls_handshaking": {
      "type": "trend",
      "contains": "time",
      "values": {
        "med": 0,
        "max": 0,
        "p(90)": 0,
        "p(95)": 0,
        "avg": 0,
        "min": 0
      }
    },
    "http_req_duration": {
      "values": {
        "p(95)": 8.45332224999999,
        "avg": 4.8385664,
        "min": 1.273261,
        "med": 3.7244384999999998,
        "max": 32.263703,
        "p(90)": 6.1832168
      },
      "thresholds": {
        "p(95)<500": {
          "ok": true
        }
      },
      "type": "trend",
      "contains": "time"
    },
    "http_req_blocked": {
      "type": "trend",
      "contains": "time",
      "values": {
        "med": 0.008862499999999999,
        "max": 0.5803,
        "p(90)": 0.011800300000000003,
        "p(95)": 0.01479564999999999,
        "avg": 0.028251633333333342,
        "min": 0.006428
      }
    },
    "http_reqs": {
      "type": "counter",
      "contains": "default",
      "values": {
        "count": 30,
        "rate": 0.9943491746932575
      }
    },
    "http_req_receiving": {
      "values": {
        "p(90)": 0.1486947,
        "p(95)": 0.154378,
        "avg": 0.10580106666666665,
        "min": 0.057039,
        "med": 0.0923095,
        "max": 0.360307
      },
      "type": "trend",
      "contains": "time"
    },
    "http_req_failed": {
      "contains": "default",
      "values": {
        "rate": 0.3333333333333333,
        "passes": 10,
        "fails": 20
      },
      "type": "rate"
    },
    "vus": {
      "type": "gauge",
      "contains": "default",
      "values": {
        "value": 1,
        "min": 1,
        "max": 1
      }
    },
    "iteration_duration": {
      "type": "trend",
      "contains": "time",
      "values": {
        "med": 3014.295497,
        "max": 3049.843749,
        "p(90)": 3018.6089942999997,
        "p(95)": 3034.22637165,
        "avg": 3017.0024535000002,
        "min": 3010.487166
      }
    },
    "http_req_sending": {
      "type": "trend",
      "contains": "time",
      "values": {
        "p(90)": 0.027844300000000013,
        "p(95)": 0.04869404999999993,
        "avg": 0.11557233333333336,
        "min": 0.017296,
        "med": 0.0219095,
        "max": 2.767968
      }
    },
    "http_req_waiting": {
      "type": "trend",
      "contains": "time",
      "values": {
        "max": 32.055506,
        "p(90)": 5.9893314,
        "p(95)": 8.28921009999999,
        "avg": 4.617192999999999,
        "min": 1.194763,
        "med": 3.436623
      }
    },
    "iterations": {
      "type": "counter",
      "contains": "default",
      "values": {
        "count": 10,
        "rate": 0.3314497248977525
      }
    },
    "checks": {
      "values": {
        "rate": 1,
        "passes": 80,
        "fails": 0
      },
      "type": "rate",
      "contains": "default"
    },
    "vus_max": {
      "type": "gauge",
      "contains": "default",
      "values": {
        "value": 1,
        "min": 1,
        "max": 1
      }
    },
    "data_received": {
      "type": "counter",
      "contains": "data",
      "values": {
        "rate": 1284.4008289512808,
        "count": 38751
      }
    },
    "errors": {
      "contains": "default",
      "values": {
        "rate": 0,
        "passes": 0,
        "fails": 30
      },
      "thresholds": {
        "rate<0.01": {
          "ok": true
        }
      },
      "type": "rate"
    },
    "http_req_connecting": {
      "type": "trend",
      "contains": "time",
      "values": {
        "p(90)": 0,
        "p(95)": 0,
        "avg": 0.016689766666666668,
        "min": 0,
        "med": 0,
        "max": 0.500693
      }
    },
    "data_sent": {
      "type": "counter",
      "contains": "data",
      "values": {
        "count": 4310,
        "rate": 142.85483143093134
      }
    },
    "http_req_duration{expected_response:true}": {
      "type": "trend",
      "contains": "time",
      "values": {
        "avg": 5.133692,
        "min": 1.273261,
        "med": 4.1267825,
        "max": 32.263703,
        "p(90)": 6.114963500000001,
        "p(95)": 7.773544700000018
      }
    }
  }
}